{
  "type": "GROUP",
"name": "Global Information",
"path": "",
"pathFormatted": "group_missing-name-b06d1",
"stats": {
    "name": "Global Information",
    "numberOfRequests": {
        "total": 750,
        "ok": 749,
        "ko": 1
    },
    "minResponseTime": {
        "total": 515,
        "ok": 515,
        "ko": 60002
    },
    "maxResponseTime": {
        "total": 60002,
        "ok": 59427,
        "ko": 60002
    },
    "meanResponseTime": {
        "total": 14699,
        "ok": 14638,
        "ko": 60002
    },
    "standardDeviation": {
        "total": 12642,
        "ok": 12541,
        "ko": 0
    },
    "percentiles1": {
        "total": 10948,
        "ok": 10936,
        "ko": 60002
    },
    "percentiles2": {
        "total": 19150,
        "ok": 18940,
        "ko": 60002
    },
    "percentiles3": {
        "total": 41915,
        "ok": 41800,
        "ko": 60002
    },
    "percentiles4": {
        "total": 54752,
        "ok": 54233,
        "ko": 60002
    },
    "group1": {
    "name": "t < 800 ms",
    "count": 6,
    "percentage": 1
},
    "group2": {
    "name": "800 ms < t < 1200 ms",
    "count": 9,
    "percentage": 1
},
    "group3": {
    "name": "t > 1200 ms",
    "count": 734,
    "percentage": 98
},
    "group4": {
    "name": "failed",
    "count": 1,
    "percentage": 0
},
    "meanNumberOfRequestsPerSecond": {
        "total": 5.0,
        "ok": 4.993333333333333,
        "ko": 0.006666666666666667
    }
},
"contents": {
"req_homepage-339f7": {
        "type": "REQUEST",
        "name": "Homepage",
"path": "Homepage",
"pathFormatted": "req_homepage-339f7",
"stats": {
    "name": "Homepage",
    "numberOfRequests": {
        "total": 150,
        "ok": 150,
        "ko": 0
    },
    "minResponseTime": {
        "total": 515,
        "ok": 515,
        "ko": 0
    },
    "maxResponseTime": {
        "total": 24150,
        "ok": 24150,
        "ko": 0
    },
    "meanResponseTime": {
        "total": 4833,
        "ok": 4833,
        "ko": 0
    },
    "standardDeviation": {
        "total": 4050,
        "ok": 4050,
        "ko": 0
    },
    "percentiles1": {
        "total": 3239,
        "ok": 3239,
        "ko": 0
    },
    "percentiles2": {
        "total": 6147,
        "ok": 6147,
        "ko": 0
    },
    "percentiles3": {
        "total": 13399,
        "ok": 13399,
        "ko": 0
    },
    "percentiles4": {
        "total": 18488,
        "ok": 18488,
        "ko": 0
    },
    "group1": {
    "name": "t < 800 ms",
    "count": 5,
    "percentage": 3
},
    "group2": {
    "name": "800 ms < t < 1200 ms",
    "count": 5,
    "percentage": 3
},
    "group3": {
    "name": "t > 1200 ms",
    "count": 140,
    "percentage": 93
},
    "group4": {
    "name": "failed",
    "count": 0,
    "percentage": 0
},
    "meanNumberOfRequestsPerSecond": {
        "total": 1.0,
        "ok": 1.0,
        "ko": 0
    }
}
    },"req_plp-page-38e14": {
        "type": "REQUEST",
        "name": "PLP PAGE",
"path": "PLP PAGE",
"pathFormatted": "req_plp-page-38e14",
"stats": {
    "name": "PLP PAGE",
    "numberOfRequests": {
        "total": 150,
        "ok": 149,
        "ko": 1
    },
    "minResponseTime": {
        "total": 2579,
        "ok": 2579,
        "ko": 60002
    },
    "maxResponseTime": {
        "total": 60002,
        "ok": 59427,
        "ko": 60002
    },
    "meanResponseTime": {
        "total": 32342,
        "ok": 32156,
        "ko": 60002
    },
    "standardDeviation": {
        "total": 15048,
        "ok": 14926,
        "ko": 0
    },
    "percentiles1": {
        "total": 35421,
        "ok": 35333,
        "ko": 60002
    },
    "percentiles2": {
        "total": 41931,
        "ok": 41872,
        "ko": 60002
    },
    "percentiles3": {
        "total": 54777,
        "ok": 54267,
        "ko": 60002
    },
    "percentiles4": {
        "total": 58864,
        "ok": 57919,
        "ko": 60002
    },
    "group1": {
    "name": "t < 800 ms",
    "count": 0,
    "percentage": 0
},
    "group2": {
    "name": "800 ms < t < 1200 ms",
    "count": 0,
    "percentage": 0
},
    "group3": {
    "name": "t > 1200 ms",
    "count": 149,
    "percentage": 99
},
    "group4": {
    "name": "failed",
    "count": 1,
    "percentage": 1
},
    "meanNumberOfRequestsPerSecond": {
        "total": 1.0,
        "ok": 0.9933333333333333,
        "ko": 0.006666666666666667
    }
}
    },"req_pdp-page-8ee17": {
        "type": "REQUEST",
        "name": "PDP Page",
"path": "PDP Page",
"pathFormatted": "req_pdp-page-8ee17",
"stats": {
    "name": "PDP Page",
    "numberOfRequests": {
        "total": 150,
        "ok": 150,
        "ko": 0
    },
    "minResponseTime": {
        "total": 1101,
        "ok": 1101,
        "ko": 0
    },
    "maxResponseTime": {
        "total": 29696,
        "ok": 29696,
        "ko": 0
    },
    "meanResponseTime": {
        "total": 13911,
        "ok": 13911,
        "ko": 0
    },
    "standardDeviation": {
        "total": 5943,
        "ok": 5943,
        "ko": 0
    },
    "percentiles1": {
        "total": 13316,
        "ok": 13316,
        "ko": 0
    },
    "percentiles2": {
        "total": 17330,
        "ok": 17330,
        "ko": 0
    },
    "percentiles3": {
        "total": 25764,
        "ok": 25764,
        "ko": 0
    },
    "percentiles4": {
        "total": 28018,
        "ok": 28018,
        "ko": 0
    },
    "group1": {
    "name": "t < 800 ms",
    "count": 0,
    "percentage": 0
},
    "group2": {
    "name": "800 ms < t < 1200 ms",
    "count": 1,
    "percentage": 1
},
    "group3": {
    "name": "t > 1200 ms",
    "count": 149,
    "percentage": 99
},
    "group4": {
    "name": "failed",
    "count": 0,
    "percentage": 0
},
    "meanNumberOfRequestsPerSecond": {
        "total": 1.0,
        "ok": 1.0,
        "ko": 0
    }
}
    },"req_add-product-to--80042": {
        "type": "REQUEST",
        "name": "Add Product to Cart",
"path": "Add Product to Cart",
"pathFormatted": "req_add-product-to--80042",
"stats": {
    "name": "Add Product to Cart",
    "numberOfRequests": {
        "total": 150,
        "ok": 150,
        "ko": 0
    },
    "minResponseTime": {
        "total": 721,
        "ok": 721,
        "ko": 0
    },
    "maxResponseTime": {
        "total": 25245,
        "ok": 25245,
        "ko": 0
    },
    "meanResponseTime": {
        "total": 8920,
        "ok": 8920,
        "ko": 0
    },
    "standardDeviation": {
        "total": 4362,
        "ok": 4362,
        "ko": 0
    },
    "percentiles1": {
        "total": 8708,
        "ok": 8708,
        "ko": 0
    },
    "percentiles2": {
        "total": 10899,
        "ok": 10899,
        "ko": 0
    },
    "percentiles3": {
        "total": 17490,
        "ok": 17490,
        "ko": 0
    },
    "percentiles4": {
        "total": 22857,
        "ok": 22857,
        "ko": 0
    },
    "group1": {
    "name": "t < 800 ms",
    "count": 1,
    "percentage": 1
},
    "group2": {
    "name": "800 ms < t < 1200 ms",
    "count": 2,
    "percentage": 1
},
    "group3": {
    "name": "t > 1200 ms",
    "count": 147,
    "percentage": 98
},
    "group4": {
    "name": "failed",
    "count": 0,
    "percentage": 0
},
    "meanNumberOfRequestsPerSecond": {
        "total": 1.0,
        "ok": 1.0,
        "ko": 0
    }
}
    },"req_proceed-to-chec-a499a": {
        "type": "REQUEST",
        "name": "Proceed to Checkout",
"path": "Proceed to Checkout",
"pathFormatted": "req_proceed-to-chec-a499a",
"stats": {
    "name": "Proceed to Checkout",
    "numberOfRequests": {
        "total": 150,
        "ok": 150,
        "ko": 0
    },
    "minResponseTime": {
        "total": 822,
        "ok": 822,
        "ko": 0
    },
    "maxResponseTime": {
        "total": 33094,
        "ok": 33094,
        "ko": 0
    },
    "meanResponseTime": {
        "total": 13487,
        "ok": 13487,
        "ko": 0
    },
    "standardDeviation": {
        "total": 7600,
        "ok": 7600,
        "ko": 0
    },
    "percentiles1": {
        "total": 12540,
        "ok": 12540,
        "ko": 0
    },
    "percentiles2": {
        "total": 18941,
        "ok": 18941,
        "ko": 0
    },
    "percentiles3": {
        "total": 27263,
        "ok": 27263,
        "ko": 0
    },
    "percentiles4": {
        "total": 32250,
        "ok": 32250,
        "ko": 0
    },
    "group1": {
    "name": "t < 800 ms",
    "count": 0,
    "percentage": 0
},
    "group2": {
    "name": "800 ms < t < 1200 ms",
    "count": 1,
    "percentage": 1
},
    "group3": {
    "name": "t > 1200 ms",
    "count": 149,
    "percentage": 99
},
    "group4": {
    "name": "failed",
    "count": 0,
    "percentage": 0
},
    "meanNumberOfRequestsPerSecond": {
        "total": 1.0,
        "ok": 1.0,
        "ko": 0
    }
}
    }
}

}